{
    "m_Version": 12,
    "DisplayName": "Delta Force Weapons Magazine",
    "Icon": "Deliver",
    "Color": "FBFCFEFF",
    "IsExchange": 0,
    "InitStockPercent": 100.0,
    "Items": [
        {
            "ClassName": "My_DF_Weapons_DMR_M14_10RndMag",
            "MaxPriceThreshold": 1000,
            "MinPriceThreshold": 1000,
            "SellPricePercent": -1,
            "MaxStockThreshold": 1,
            "MinStockThreshold": 1,
            "QuantityPercent": -1,
            "SpawnAttachments": [],
            "Variants": []
        },
        {
            "ClassName": "My_DF_Weapons_DMR_M14_20RndMag",
            "MaxPriceThreshold": 1000,
            "MinPriceThreshold": 1000,
            "SellPricePercent": -1,
            "MaxStockThreshold": 1,
            "MinStockThreshold": 1,
            "QuantityPercent": -1,
            "SpawnAttachments": [],
            "Variants": []
        },
        {
            "ClassName": "My_DF_Weapons_DMR_M14_50RndMag",
            "MaxPriceThreshold": 1000,
            "MinPriceThreshold": 1000,
            "SellPricePercent": -1,
            "MaxStockThreshold": 1,
            "MinStockThreshold": 1,
            "QuantityPercent": -1,
            "SpawnAttachments": [],
            "Variants": []
        },
        {
            "ClassName": "My_DF_Weapons_DMR_Mini14_10RndMag",
            "MaxPriceThreshold": 1000,
            "MinPriceThreshold": 1000,
            "SellPricePercent": -1,
            "MaxStockThreshold": 1,
            "MinStockThreshold": 1,
            "QuantityPercent": -1,
            "SpawnAttachments": [],
            "Variants": []
        },
        {
            "ClassName": "My_DF_Weapons_DMR_Mini14_20RndMag",
            "MaxPriceThreshold": 1000,
            "MinPriceThreshold": 1000,
            "SellPricePercent": -1,
            "MaxStockThreshold": 1,
            "MinStockThreshold": 1,
            "QuantityPercent": -1,
            "SpawnAttachments": [],
            "Variants": []
        },
        {
            "ClassName": "My_DF_Weapons_DMR_Mini14_30RndMag",
            "MaxPriceThreshold": 1000,
            "MinPriceThreshold": 1000,
            "SellPricePercent": -1,
            "MaxStockThreshold": 1,
            "MinStockThreshold": 1,
            "QuantityPercent": -1,
            "SpawnAttachments": [],
            "Variants": []
        },
        {
            "ClassName": "My_DF_Weapons_DMR_SR25_10RndMag",
            "MaxPriceThreshold": 1000,
            "MinPriceThreshold": 1000,
            "SellPricePercent": -1,
            "MaxStockThreshold": 1,
            "MinStockThreshold": 1,
            "QuantityPercent": -1,
            "SpawnAttachments": [],
            "Variants": []
        },
        {
            "ClassName": "My_DF_Weapons_DMR_SR25_20RndMag",
            "MaxPriceThreshold": 1000,
            "MinPriceThreshold": 1000,
            "SellPricePercent": -1,
            "MaxStockThreshold": 1,
            "MinStockThreshold": 1,
            "QuantityPercent": -1,
            "SpawnAttachments": [],
            "Variants": []
        },
        {
            "ClassName": "My_DF_Weapons_DMR_SVD_10RndMag",
            "MaxPriceThreshold": 1000,
            "MinPriceThreshold": 1000,
            "SellPricePercent": -1,
            "MaxStockThreshold": 1,
            "MinStockThreshold": 1,
            "QuantityPercent": -1,
            "SpawnAttachments": [],
            "Variants": []
        },
        {
            "ClassName": "My_DF_Weapons_DMR_SVD_20RndMag",
            "MaxPriceThreshold": 1000,
            "MinPriceThreshold": 1000,
            "SellPricePercent": -1,
            "MaxStockThreshold": 1,
            "MinStockThreshold": 1,
            "QuantityPercent": -1,
            "SpawnAttachments": [],
            "Variants": []
        },
        {
            "ClassName": "My_DF_Weapons_DMR_VSS_10RndMag",
            "MaxPriceThreshold": 1000,
            "MinPriceThreshold": 1000,
            "SellPricePercent": -1,
            "MaxStockThreshold": 1,
            "MinStockThreshold": 1,
            "QuantityPercent": -1,
            "SpawnAttachments": [],
            "Variants": []
        },
        {
            "ClassName": "My_DF_Weapons_DMR_VSS_30RndMag",
            "MaxPriceThreshold": 1000,
            "MinPriceThreshold": 1000,
            "SellPricePercent": -1,
            "MaxStockThreshold": 1,
            "MinStockThreshold": 1,
            "QuantityPercent": -1,
            "SpawnAttachments": [],
            "Variants": []
        },
        {
            "ClassName": "My_DF_Weapons_DMR_VSS_45RndMag",
            "MaxPriceThreshold": 1000,
            "MinPriceThreshold": 1000,
            "SellPricePercent": -1,
            "MaxStockThreshold": 1,
            "MinStockThreshold": 1,
            "QuantityPercent": -1,
            "SpawnAttachments": [],
            "Variants": []
        },
        {
            "ClassName": "My_DF_Weapons_LMG_M249_100RndMag",
            "MaxPriceThreshold": 1000,
            "MinPriceThreshold": 1000,
            "SellPricePercent": -1,
            "MaxStockThreshold": 1,
            "MinStockThreshold": 1,
            "QuantityPercent": -1,
            "SpawnAttachments": [],
            "Variants": []
        },
        {
            "ClassName": "My_DF_Weapons_LMG_M250_125RndMag",
            "MaxPriceThreshold": 1000,
            "MinPriceThreshold": 1000,
            "SellPricePercent": -1,
            "MaxStockThreshold": 1,
            "MinStockThreshold": 1,
            "QuantityPercent": -1,
            "SpawnAttachments": [],
            "Variants": []
        },
        {
            "ClassName": "My_DF_Weapons_LMG_M250_75RndMag",
            "MaxPriceThreshold": 1000,
            "MinPriceThreshold": 1000,
            "SellPricePercent": -1,
            "MaxStockThreshold": 1,
            "MinStockThreshold": 1,
            "QuantityPercent": -1,
            "SpawnAttachments": [],
            "Variants": []
        },
        {
            "ClassName": "My_DF_Weapons_LMG_PKM_125RndMag",
            "MaxPriceThreshold": 1000,
            "MinPriceThreshold": 1000,
            "SellPricePercent": -1,
            "MaxStockThreshold": 1,
            "MinStockThreshold": 1,
            "QuantityPercent": -1,
            "SpawnAttachments": [],
            "Variants": []
        },
        {
            "ClassName": "My_DF_Weapons_LMG_PKM_75RndMag",
            "MaxPriceThreshold": 1000,
            "MinPriceThreshold": 1000,
            "SellPricePercent": -1,
            "MaxStockThreshold": 1,
            "MinStockThreshold": 1,
            "QuantityPercent": -1,
            "SpawnAttachments": [],
            "Variants": []
        },
        {
            "ClassName": "My_DF_Weapons_LMG_QJB201_125RndMag",
            "MaxPriceThreshold": 1000,
            "MinPriceThreshold": 1000,
            "SellPricePercent": -1,
            "MaxStockThreshold": 1,
            "MinStockThreshold": 1,
            "QuantityPercent": -1,
            "SpawnAttachments": [],
            "Variants": []
        },
        {
            "ClassName": "My_DF_Weapons_LMG_QJB201_45RndMag",
            "MaxPriceThreshold": 1000,
            "MinPriceThreshold": 1000,
            "SellPricePercent": -1,
            "MaxStockThreshold": 1,
            "MinStockThreshold": 1,
            "QuantityPercent": -1,
            "SpawnAttachments": [],
            "Variants": []
        },
        {
            "ClassName": "My_DF_Weapons_Pistols_93R_12RndMag",
            "MaxPriceThreshold": 1000,
            "MinPriceThreshold": 1000,
            "SellPricePercent": -1,
            "MaxStockThreshold": 1,
            "MinStockThreshold": 1,
            "QuantityPercent": -1,
            "SpawnAttachments": [],
            "Variants": []
        },
        {
            "ClassName": "My_DF_Weapons_Pistols_93R_18RndExtMag",
            "MaxPriceThreshold": 1000,
            "MinPriceThreshold": 1000,
            "SellPricePercent": -1,
            "MaxStockThreshold": 1,
            "MinStockThreshold": 1,
            "QuantityPercent": -1,
            "SpawnAttachments": [],
            "Variants": []
        },
        {
            "ClassName": "My_DF_Weapons_Pistols_93R_24RndExtMag",
            "MaxPriceThreshold": 1000,
            "MinPriceThreshold": 1000,
            "SellPricePercent": -1,
            "MaxStockThreshold": 1,
            "MinStockThreshold": 1,
            "QuantityPercent": -1,
            "SpawnAttachments": [],
            "Variants": []
        },
        {
            "ClassName": "My_DF_Weapons_Pistols_Deagle_13RndMag",
            "MaxPriceThreshold": 1000,
            "MinPriceThreshold": 1000,
            "SellPricePercent": -1,
            "MaxStockThreshold": 1,
            "MinStockThreshold": 1,
            "QuantityPercent": -1,
            "SpawnAttachments": [],
            "Variants": []
        },
        {
            "ClassName": "My_DF_Weapons_Pistols_Deagle_7RndMag",
            "MaxPriceThreshold": 1000,
            "MinPriceThreshold": 1000,
            "SellPricePercent": -1,
            "MaxStockThreshold": 1,
            "MinStockThreshold": 1,
            "QuantityPercent": -1,
            "SpawnAttachments": [],
            "Variants": []
        },
        {
            "ClassName": "My_DF_Weapons_Pistols_Glock18C_17RndMag",
            "MaxPriceThreshold": 1000,
            "MinPriceThreshold": 1000,
            "SellPricePercent": -1,
            "MaxStockThreshold": 1,
            "MinStockThreshold": 1,
            "QuantityPercent": -1,
            "SpawnAttachments": [],
            "Variants": []
        },
        {
            "ClassName": "My_DF_Weapons_Pistols_Glock18C_25RndExtMag",
            "MaxPriceThreshold": 1000,
            "MinPriceThreshold": 1000,
            "SellPricePercent": -1,
            "MaxStockThreshold": 1,
            "MinStockThreshold": 1,
            "QuantityPercent": -1,
            "SpawnAttachments": [],
            "Variants": []
        },
        {
            "ClassName": "My_DF_Weapons_Pistols_Glock18C_33RndExtMag",
            "MaxPriceThreshold": 1000,
            "MinPriceThreshold": 1000,
            "SellPricePercent": -1,
            "MaxStockThreshold": 1,
            "MinStockThreshold": 1,
            "QuantityPercent": -1,
            "SpawnAttachments": [],
            "Variants": []
        },
        {
            "ClassName": "My_DF_Weapons_Pistols_M1911_11RndExtMag",
            "MaxPriceThreshold": 1000,
            "MinPriceThreshold": 1000,
            "SellPricePercent": -1,
            "MaxStockThreshold": 1,
            "MinStockThreshold": 1,
            "QuantityPercent": -1,
            "SpawnAttachments": [],
            "Variants": []
        },
        {
            "ClassName": "My_DF_Weapons_Pistols_M1911_7RndMag",
            "MaxPriceThreshold": 1000,
            "MinPriceThreshold": 1000,
            "SellPricePercent": -1,
            "MaxStockThreshold": 1,
            "MinStockThreshold": 1,
            "QuantityPercent": -1,
            "SpawnAttachments": [],
            "Variants": []
        },
        {
            "ClassName": "My_DF_Weapons_Pistols_QSZ92G_15RndMag",
            "MaxPriceThreshold": 1000,
            "MinPriceThreshold": 1000,
            "SellPricePercent": -1,
            "MaxStockThreshold": 1,
            "MinStockThreshold": 1,
            "QuantityPercent": -1,
            "SpawnAttachments": [],
            "Variants": []
        },
        {
            "ClassName": "My_DF_Weapons_Rifles_AK12_30RndMag",
            "MaxPriceThreshold": 1000,
            "MinPriceThreshold": 1000,
            "SellPricePercent": -1,
            "MaxStockThreshold": 1,
            "MinStockThreshold": 1,
            "QuantityPercent": -1,
            "SpawnAttachments": [],
            "Variants": []
        },
        {
            "ClassName": "My_DF_Weapons_Rifles_AK74_20RndMag",
            "MaxPriceThreshold": 1000,
            "MinPriceThreshold": 1000,
            "SellPricePercent": -1,
            "MaxStockThreshold": 1,
            "MinStockThreshold": 1,
            "QuantityPercent": -1,
            "SpawnAttachments": [],
            "Variants": []
        },
        {
            "ClassName": "My_DF_Weapons_Rifles_AK74_30RndMag",
            "MaxPriceThreshold": 1000,
            "MinPriceThreshold": 1000,
            "SellPricePercent": -1,
            "MaxStockThreshold": 1,
            "MinStockThreshold": 1,
            "QuantityPercent": -1,
            "SpawnAttachments": [],
            "Variants": []
        },
        {
            "ClassName": "My_DF_Weapons_Rifles_AKM_20RndMag",
            "MaxPriceThreshold": 1000,
            "MinPriceThreshold": 1000,
            "SellPricePercent": -1,
            "MaxStockThreshold": 1,
            "MinStockThreshold": 1,
            "QuantityPercent": -1,
            "SpawnAttachments": [],
            "Variants": []
        },
        {
            "ClassName": "My_DF_Weapons_Rifles_AKM_30RndMag2",
            "MaxPriceThreshold": 1000,
            "MinPriceThreshold": 1000,
            "SellPricePercent": -1,
            "MaxStockThreshold": 1,
            "MinStockThreshold": 1,
            "QuantityPercent": -1,
            "SpawnAttachments": [],
            "Variants": []
        },
        {
            "ClassName": "My_DF_Weapons_Rifles_AKM_30RndMag3",
            "MaxPriceThreshold": 1000,
            "MinPriceThreshold": 1000,
            "SellPricePercent": -1,
            "MaxStockThreshold": 1,
            "MinStockThreshold": 1,
            "QuantityPercent": -1,
            "SpawnAttachments": [],
            "Variants": []
        },
        {
            "ClassName": "My_DF_Weapons_Rifles_AKM_30RndMag",
            "MaxPriceThreshold": 1000,
            "MinPriceThreshold": 1000,
            "SellPricePercent": -1,
            "MaxStockThreshold": 1,
            "MinStockThreshold": 1,
            "QuantityPercent": -1,
            "SpawnAttachments": [],
            "Variants": []
        },
        {
            "ClassName": "My_DF_Weapons_Rifles_AKM_40RndMag",
            "MaxPriceThreshold": 1000,
            "MinPriceThreshold": 1000,
            "SellPricePercent": -1,
            "MaxStockThreshold": 1,
            "MinStockThreshold": 1,
            "QuantityPercent": -1,
            "SpawnAttachments": [],
            "Variants": []
        },
        {
            "ClassName": "My_DF_Weapons_Rifles_AKM_70RndMag",
            "MaxPriceThreshold": 1000,
            "MinPriceThreshold": 1000,
            "SellPricePercent": -1,
            "MaxStockThreshold": 1,
            "MinStockThreshold": 1,
            "QuantityPercent": -1,
            "SpawnAttachments": [],
            "Variants": []
        },
        {
            "ClassName": "My_DF_Weapons_Rifles_AKS74U_30RndMag",
            "MaxPriceThreshold": 1000,
            "MinPriceThreshold": 1000,
            "SellPricePercent": -1,
            "MaxStockThreshold": 1,
            "MinStockThreshold": 1,
            "QuantityPercent": -1,
            "SpawnAttachments": [],
            "Variants": []
        },
        {
            "ClassName": "My_DF_Weapons_Rifles_AKS74U_45RndExtMag",
            "MaxPriceThreshold": 1000,
            "MinPriceThreshold": 1000,
            "SellPricePercent": -1,
            "MaxStockThreshold": 1,
            "MinStockThreshold": 1,
            "QuantityPercent": -1,
            "SpawnAttachments": [],
            "Variants": []
        },
        {
            "ClassName": "My_DF_Weapons_Rifles_AKS74U_75RndDrumMag",
            "MaxPriceThreshold": 1000,
            "MinPriceThreshold": 1000,
            "SellPricePercent": -1,
            "MaxStockThreshold": 1,
            "MinStockThreshold": 1,
            "QuantityPercent": -1,
            "SpawnAttachments": [],
            "Variants": []
        },
        {
            "ClassName": "My_DF_Weapons_Rifles_Ash12_20RndMag",
            "MaxPriceThreshold": 1000,
            "MinPriceThreshold": 1000,
            "SellPricePercent": -1,
            "MaxStockThreshold": 1,
            "MinStockThreshold": 1,
            "QuantityPercent": -1,
            "SpawnAttachments": [],
            "Variants": []
        },
        {
            "ClassName": "My_DF_Weapons_Rifles_Ash12_30RndMag",
            "MaxPriceThreshold": 1000,
            "MinPriceThreshold": 1000,
            "SellPricePercent": -1,
            "MaxStockThreshold": 1,
            "MinStockThreshold": 1,
            "QuantityPercent": -1,
            "SpawnAttachments": [],
            "Variants": []
        },
        {
            "ClassName": "My_DF_Weapons_Rifles_AUG_30RndMag",
            "MaxPriceThreshold": 1000,
            "MinPriceThreshold": 1000,
            "SellPricePercent": -1,
            "MaxStockThreshold": 1,
            "MinStockThreshold": 1,
            "QuantityPercent": -1,
            "SpawnAttachments": [],
            "Variants": []
        },
        {
            "ClassName": "My_DF_Weapons_Rifles_AUG_30RndPMag",
            "MaxPriceThreshold": 1000,
            "MinPriceThreshold": 1000,
            "SellPricePercent": -1,
            "MaxStockThreshold": 1,
            "MinStockThreshold": 1,
            "QuantityPercent": -1,
            "SpawnAttachments": [],
            "Variants": []
        },
        {
            "ClassName": "My_DF_Weapons_Rifles_AUG_60RndMag",
            "MaxPriceThreshold": 1000,
            "MinPriceThreshold": 1000,
            "SellPricePercent": -1,
            "MaxStockThreshold": 1,
            "MinStockThreshold": 1,
            "QuantityPercent": -1,
            "SpawnAttachments": [],
            "Variants": []
        },
        {
            "ClassName": "My_DF_Weapons_Rifles_G3_10RndMag",
            "MaxPriceThreshold": 1000,
            "MinPriceThreshold": 1000,
            "SellPricePercent": -1,
            "MaxStockThreshold": 1,
            "MinStockThreshold": 1,
            "QuantityPercent": -1,
            "SpawnAttachments": [],
            "Variants": []
        },
        {
            "ClassName": "My_DF_Weapons_Rifles_G3_20RndMag",
            "MaxPriceThreshold": 1000,
            "MinPriceThreshold": 1000,
            "SellPricePercent": -1,
            "MaxStockThreshold": 1,
            "MinStockThreshold": 1,
            "QuantityPercent": -1,
            "SpawnAttachments": [],
            "Variants": []
        },
        {
            "ClassName": "My_DF_Weapons_Rifles_G3_30RndMag",
            "MaxPriceThreshold": 1000,
            "MinPriceThreshold": 1000,
            "SellPricePercent": -1,
            "MaxStockThreshold": 1,
            "MinStockThreshold": 1,
            "QuantityPercent": -1,
            "SpawnAttachments": [],
            "Variants": []
        },
        {
            "ClassName": "My_DF_Weapons_Rifles_G3_50RndDrumMag",
            "MaxPriceThreshold": 1000,
            "MinPriceThreshold": 1000,
            "SellPricePercent": -1,
            "MaxStockThreshold": 1,
            "MinStockThreshold": 1,
            "QuantityPercent": -1,
            "SpawnAttachments": [],
            "Variants": []
        },
        {
            "ClassName": "My_DF_Weapons_Rifles_K437_30RndMag",
            "MaxPriceThreshold": 1000,
            "MinPriceThreshold": 1000,
            "SellPricePercent": -1,
            "MaxStockThreshold": 1,
            "MinStockThreshold": 1,
            "QuantityPercent": -1,
            "SpawnAttachments": [],
            "Variants": []
        },
        {
            "ClassName": "My_DF_Weapons_Rifles_K437_45RndMag",
            "MaxPriceThreshold": 1000,
            "MinPriceThreshold": 1000,
            "SellPricePercent": -1,
            "MaxStockThreshold": 1,
            "MinStockThreshold": 1,
            "QuantityPercent": -1,
            "SpawnAttachments": [],
            "Variants": []
        },
        {
            "ClassName": "My_DF_Weapons_Rifles_K437_60RndMag",
            "MaxPriceThreshold": 1000,
            "MinPriceThreshold": 1000,
            "SellPricePercent": -1,
            "MaxStockThreshold": 1,
            "MinStockThreshold": 1,
            "QuantityPercent": -1,
            "SpawnAttachments": [],
            "Variants": []
        },
        {
            "ClassName": "My_DF_Weapons_Rifles_KC17_30RndMag",
            "MaxPriceThreshold": 1000,
            "MinPriceThreshold": 1000,
            "SellPricePercent": -1,
            "MaxStockThreshold": 1,
            "MinStockThreshold": 1,
            "QuantityPercent": -1,
            "SpawnAttachments": [],
            "Variants": []
        },
        {
            "ClassName": "My_DF_Weapons_Rifles_KC17_45RndMag",
            "MaxPriceThreshold": 1000,
            "MinPriceThreshold": 1000,
            "SellPricePercent": -1,
            "MaxStockThreshold": 1,
            "MinStockThreshold": 1,
            "QuantityPercent": -1,
            "SpawnAttachments": [],
            "Variants": []
        },
        {
            "ClassName": "My_DF_Weapons_Rifles_KC17_75RndMag",
            "MaxPriceThreshold": 1000,
            "MinPriceThreshold": 1000,
            "SellPricePercent": -1,
            "MaxStockThreshold": 1,
            "MinStockThreshold": 1,
            "QuantityPercent": -1,
            "SpawnAttachments": [],
            "Variants": []
        },
        {
            "ClassName": "My_DF_Weapons_Rifles_M4A1_20RndMag",
            "MaxPriceThreshold": 1000,
            "MinPriceThreshold": 1000,
            "SellPricePercent": -1,
            "MaxStockThreshold": 1,
            "MinStockThreshold": 1,
            "QuantityPercent": -1,
            "SpawnAttachments": [],
            "Variants": []
        },
        {
            "ClassName": "My_DF_Weapons_Rifles_M4A1_30RndMag2",
            "MaxPriceThreshold": 1000,
            "MinPriceThreshold": 1000,
            "SellPricePercent": -1,
            "MaxStockThreshold": 1,
            "MinStockThreshold": 1,
            "QuantityPercent": -1,
            "SpawnAttachments": [],
            "Variants": []
        },
        {
            "ClassName": "My_DF_Weapons_Rifles_M4A1_30RndMag",
            "MaxPriceThreshold": 1000,
            "MinPriceThreshold": 1000,
            "SellPricePercent": -1,
            "MaxStockThreshold": 1,
            "MinStockThreshold": 1,
            "QuantityPercent": -1,
            "SpawnAttachments": [],
            "Variants": []
        },
        {
            "ClassName": "My_DF_Weapons_Rifles_M4A1_30RndPMag",
            "MaxPriceThreshold": 1000,
            "MinPriceThreshold": 1000,
            "SellPricePercent": -1,
            "MaxStockThreshold": 1,
            "MinStockThreshold": 1,
            "QuantityPercent": -1,
            "SpawnAttachments": [],
            "Variants": []
        },
        {
            "ClassName": "My_DF_Weapons_Rifles_M4A1_45RndMag",
            "MaxPriceThreshold": 1000,
            "MinPriceThreshold": 1000,
            "SellPricePercent": -1,
            "MaxStockThreshold": 1,
            "MinStockThreshold": 1,
            "QuantityPercent": -1,
            "SpawnAttachments": [],
            "Variants": []
        },
        {
            "ClassName": "My_DF_Weapons_Rifles_M4A1_60RndDrumMag",
            "MaxPriceThreshold": 1000,
            "MinPriceThreshold": 1000,
            "SellPricePercent": -1,
            "MaxStockThreshold": 1,
            "MinStockThreshold": 1,
            "QuantityPercent": -1,
            "SpawnAttachments": [],
            "Variants": []
        },
        {
            "ClassName": "My_DF_Weapons_Rifles_M4A1_60RndMag",
            "MaxPriceThreshold": 1000,
            "MinPriceThreshold": 1000,
            "SellPricePercent": -1,
            "MaxStockThreshold": 1,
            "MinStockThreshold": 1,
            "QuantityPercent": -1,
            "SpawnAttachments": [],
            "Variants": []
        },
        {
            "ClassName": "My_DF_Weapons_Rifles_M7_20RndMag",
            "MaxPriceThreshold": 1000,
            "MinPriceThreshold": 1000,
            "SellPricePercent": -1,
            "MaxStockThreshold": 1,
            "MinStockThreshold": 1,
            "QuantityPercent": -1,
            "SpawnAttachments": [],
            "Variants": []
        },
        {
            "ClassName": "My_DF_Weapons_Rifles_M7_30RndMag",
            "MaxPriceThreshold": 1000,
            "MinPriceThreshold": 1000,
            "SellPricePercent": -1,
            "MaxStockThreshold": 1,
            "MinStockThreshold": 1,
            "QuantityPercent": -1,
            "SpawnAttachments": [],
            "Variants": []
        },
        {
            "ClassName": "My_DF_Weapons_Rifles_M7_45RndMag",
            "MaxPriceThreshold": 1000,
            "MinPriceThreshold": 1000,
            "SellPricePercent": -1,
            "MaxStockThreshold": 1,
            "MinStockThreshold": 1,
            "QuantityPercent": -1,
            "SpawnAttachments": [],
            "Variants": []
        },
        {
            "ClassName": "My_DF_Weapons_Rifles_PTR32_30RndMag",
            "MaxPriceThreshold": 1000,
            "MinPriceThreshold": 1000,
            "SellPricePercent": -1,
            "MaxStockThreshold": 1,
            "MinStockThreshold": 1,
            "QuantityPercent": -1,
            "SpawnAttachments": [],
            "Variants": []
        },
        {
            "ClassName": "My_DF_Weapons_Rifles_QBZ191_30RndMag",
            "MaxPriceThreshold": 1000,
            "MinPriceThreshold": 1000,
            "SellPricePercent": -1,
            "MaxStockThreshold": 1,
            "MinStockThreshold": 1,
            "QuantityPercent": -1,
            "SpawnAttachments": [],
            "Variants": []
        },
        {
            "ClassName": "My_DF_Weapons_Rifles_QBZ191_60RndMag",
            "MaxPriceThreshold": 1000,
            "MinPriceThreshold": 1000,
            "SellPricePercent": -1,
            "MaxStockThreshold": 1,
            "MinStockThreshold": 1,
            "QuantityPercent": -1,
            "SpawnAttachments": [],
            "Variants": []
        },
        {
            "ClassName": "My_DF_Weapons_Rifles_QBZ95_30RndMag",
            "MaxPriceThreshold": 1000,
            "MinPriceThreshold": 1000,
            "SellPricePercent": -1,
            "MaxStockThreshold": 1,
            "MinStockThreshold": 1,
            "QuantityPercent": -1,
            "SpawnAttachments": [],
            "Variants": []
        },
        {
            "ClassName": "My_DF_Weapons_Rifles_SCARH_20RndMag",
            "MaxPriceThreshold": 1000,
            "MinPriceThreshold": 1000,
            "SellPricePercent": -1,
            "MaxStockThreshold": 1,
            "MinStockThreshold": 1,
            "QuantityPercent": -1,
            "SpawnAttachments": [],
            "Variants": []
        },
        {
            "ClassName": "My_DF_Weapons_Rifles_SCARH_30RndMag",
            "MaxPriceThreshold": 1000,
            "MinPriceThreshold": 1000,
            "SellPricePercent": -1,
            "MaxStockThreshold": 1,
            "MinStockThreshold": 1,
            "QuantityPercent": -1,
            "SpawnAttachments": [],
            "Variants": []
        },
        {
            "ClassName": "My_DF_Weapons_Rifles_SCARH_50RndMag",
            "MaxPriceThreshold": 1000,
            "MinPriceThreshold": 1000,
            "SellPricePercent": -1,
            "MaxStockThreshold": 1,
            "MinStockThreshold": 1,
            "QuantityPercent": -1,
            "SpawnAttachments": [],
            "Variants": []
        },
        {
            "ClassName": "My_DF_Weapons_Rifles_SG553_20RndMag",
            "MaxPriceThreshold": 1000,
            "MinPriceThreshold": 1000,
            "SellPricePercent": -1,
            "MaxStockThreshold": 1,
            "MinStockThreshold": 1,
            "QuantityPercent": -1,
            "SpawnAttachments": [],
            "Variants": []
        },
        {
            "ClassName": "My_DF_Weapons_Rifles_SG553_30RndMag",
            "MaxPriceThreshold": 1000,
            "MinPriceThreshold": 1000,
            "SellPricePercent": -1,
            "MaxStockThreshold": 1,
            "MinStockThreshold": 1,
            "QuantityPercent": -1,
            "SpawnAttachments": [],
            "Variants": []
        },
        {
            "ClassName": "My_DF_Weapons_Rifles_SG553_45RndMag",
            "MaxPriceThreshold": 1000,
            "MinPriceThreshold": 1000,
            "SellPricePercent": -1,
            "MaxStockThreshold": 1,
            "MinStockThreshold": 1,
            "QuantityPercent": -1,
            "SpawnAttachments": [],
            "Variants": []
        },
        {
            "ClassName": "My_DF_Weapons_Shotguns_Saiga12K_10RndMag",
            "MaxPriceThreshold": 1000,
            "MinPriceThreshold": 1000,
            "SellPricePercent": -1,
            "MaxStockThreshold": 1,
            "MinStockThreshold": 1,
            "QuantityPercent": -1,
            "SpawnAttachments": [],
            "Variants": []
        },
        {
            "ClassName": "My_DF_Weapons_Shotguns_Saiga12K_24RndDrumMag",
            "MaxPriceThreshold": 1000,
            "MinPriceThreshold": 1000,
            "SellPricePercent": -1,
            "MaxStockThreshold": 1,
            "MinStockThreshold": 1,
            "QuantityPercent": -1,
            "SpawnAttachments": [],
            "Variants": []
        },
        {
            "ClassName": "My_DF_Weapons_Shotguns_Saiga12K_5RndMag",
            "MaxPriceThreshold": 1000,
            "MinPriceThreshold": 1000,
            "SellPricePercent": -1,
            "MaxStockThreshold": 1,
            "MinStockThreshold": 1,
            "QuantityPercent": -1,
            "SpawnAttachments": [],
            "Variants": []
        },
        {
            "ClassName": "My_DF_Weapons_SMG_Bison_32RndMag",
            "MaxPriceThreshold": 1000,
            "MinPriceThreshold": 1000,
            "SellPricePercent": -1,
            "MaxStockThreshold": 1,
            "MinStockThreshold": 1,
            "QuantityPercent": -1,
            "SpawnAttachments": [],
            "Variants": []
        },
        {
            "ClassName": "My_DF_Weapons_SMG_Bison_64RndMag",
            "MaxPriceThreshold": 1000,
            "MinPriceThreshold": 1000,
            "SellPricePercent": -1,
            "MaxStockThreshold": 1,
            "MinStockThreshold": 1,
            "QuantityPercent": -1,
            "SpawnAttachments": [],
            "Variants": []
        },
        {
            "ClassName": "My_DF_Weapons_SMG_MP5_20RndMag",
            "MaxPriceThreshold": 1000,
            "MinPriceThreshold": 1000,
            "SellPricePercent": -1,
            "MaxStockThreshold": 1,
            "MinStockThreshold": 1,
            "QuantityPercent": -1,
            "SpawnAttachments": [],
            "Variants": []
        },
        {
            "ClassName": "My_DF_Weapons_SMG_MP5_30RndMag",
            "MaxPriceThreshold": 1000,
            "MinPriceThreshold": 1000,
            "SellPricePercent": -1,
            "MaxStockThreshold": 1,
            "MinStockThreshold": 1,
            "QuantityPercent": -1,
            "SpawnAttachments": [],
            "Variants": []
        },
        {
            "ClassName": "My_DF_Weapons_SMG_MP5_50RndMag",
            "MaxPriceThreshold": 1000,
            "MinPriceThreshold": 1000,
            "SellPricePercent": -1,
            "MaxStockThreshold": 1,
            "MinStockThreshold": 1,
            "QuantityPercent": -1,
            "SpawnAttachments": [],
            "Variants": []
        },
        {
            "ClassName": "My_DF_Weapons_SMG_MP7_20RndMag",
            "MaxPriceThreshold": 1000,
            "MinPriceThreshold": 1000,
            "SellPricePercent": -1,
            "MaxStockThreshold": 1,
            "MinStockThreshold": 1,
            "QuantityPercent": -1,
            "SpawnAttachments": [],
            "Variants": []
        },
        {
            "ClassName": "My_DF_Weapons_SMG_MP7_30RndMag",
            "MaxPriceThreshold": 1000,
            "MinPriceThreshold": 1000,
            "SellPricePercent": -1,
            "MaxStockThreshold": 1,
            "MinStockThreshold": 1,
            "QuantityPercent": -1,
            "SpawnAttachments": [],
            "Variants": []
        },
        {
            "ClassName": "My_DF_Weapons_SMG_MP7_40RndMag",
            "MaxPriceThreshold": 1000,
            "MinPriceThreshold": 1000,
            "SellPricePercent": -1,
            "MaxStockThreshold": 1,
            "MinStockThreshold": 1,
            "QuantityPercent": -1,
            "SpawnAttachments": [],
            "Variants": []
        },
        {
            "ClassName": "My_DF_Weapons_SMG_MP7_60RndMag",
            "MaxPriceThreshold": 1000,
            "MinPriceThreshold": 1000,
            "SellPricePercent": -1,
            "MaxStockThreshold": 1,
            "MinStockThreshold": 1,
            "QuantityPercent": -1,
            "SpawnAttachments": [],
            "Variants": []
        },
        {
            "ClassName": "My_DF_Weapons_SMG_P90_50RndMag",
            "MaxPriceThreshold": 1000,
            "MinPriceThreshold": 1000,
            "SellPricePercent": -1,
            "MaxStockThreshold": 1,
            "MinStockThreshold": 1,
            "QuantityPercent": -1,
            "SpawnAttachments": [],
            "Variants": []
        },
        {
            "ClassName": "My_DF_Weapons_SMG_PP19_30RndMag",
            "MaxPriceThreshold": 1000,
            "MinPriceThreshold": 1000,
            "SellPricePercent": -1,
            "MaxStockThreshold": 1,
            "MinStockThreshold": 1,
            "QuantityPercent": -1,
            "SpawnAttachments": [],
            "Variants": []
        },
        {
            "ClassName": "My_DF_Weapons_SMG_PP19_45RndMag",
            "MaxPriceThreshold": 1000,
            "MinPriceThreshold": 1000,
            "SellPricePercent": -1,
            "MaxStockThreshold": 1,
            "MinStockThreshold": 1,
            "QuantityPercent": -1,
            "SpawnAttachments": [],
            "Variants": []
        },
        {
            "ClassName": "My_DF_Weapons_SMG_QCQ171_100RndMag",
            "MaxPriceThreshold": 1000,
            "MinPriceThreshold": 1000,
            "SellPricePercent": -1,
            "MaxStockThreshold": 1,
            "MinStockThreshold": 1,
            "QuantityPercent": -1,
            "SpawnAttachments": [],
            "Variants": []
        },
        {
            "ClassName": "My_DF_Weapons_SMG_QCQ171_30RndMag",
            "MaxPriceThreshold": 1000,
            "MinPriceThreshold": 1000,
            "SellPricePercent": -1,
            "MaxStockThreshold": 1,
            "MinStockThreshold": 1,
            "QuantityPercent": -1,
            "SpawnAttachments": [],
            "Variants": []
        },
        {
            "ClassName": "My_DF_Weapons_SMG_QCQ171_45RndMag",
            "MaxPriceThreshold": 1000,
            "MinPriceThreshold": 1000,
            "SellPricePercent": -1,
            "MaxStockThreshold": 1,
            "MinStockThreshold": 1,
            "QuantityPercent": -1,
            "SpawnAttachments": [],
            "Variants": []
        },
        {
            "ClassName": "My_DF_Weapons_SMG_SMG45_25RndMag",
            "MaxPriceThreshold": 1000,
            "MinPriceThreshold": 1000,
            "SellPricePercent": -1,
            "MaxStockThreshold": 1,
            "MinStockThreshold": 1,
            "QuantityPercent": -1,
            "SpawnAttachments": [],
            "Variants": []
        },
        {
            "ClassName": "My_DF_Weapons_SMG_SMG45_40RndMag",
            "MaxPriceThreshold": 1000,
            "MinPriceThreshold": 1000,
            "SellPricePercent": -1,
            "MaxStockThreshold": 1,
            "MinStockThreshold": 1,
            "QuantityPercent": -1,
            "SpawnAttachments": [],
            "Variants": []
        },
        {
            "ClassName": "My_DF_Weapons_SMG_Uzi_25RndMag",
            "MaxPriceThreshold": 1000,
            "MinPriceThreshold": 1000,
            "SellPricePercent": -1,
            "MaxStockThreshold": 1,
            "MinStockThreshold": 1,
            "QuantityPercent": -1,
            "SpawnAttachments": [],
            "Variants": []
        },
        {
            "ClassName": "My_DF_Weapons_SMG_Uzi_35RndMag",
            "MaxPriceThreshold": 1000,
            "MinPriceThreshold": 1000,
            "SellPricePercent": -1,
            "MaxStockThreshold": 1,
            "MinStockThreshold": 1,
            "QuantityPercent": -1,
            "SpawnAttachments": [],
            "Variants": []
        },
        {
            "ClassName": "My_DF_Weapons_SMG_Uzi_45RndMag",
            "MaxPriceThreshold": 1000,
            "MinPriceThreshold": 1000,
            "SellPricePercent": -1,
            "MaxStockThreshold": 1,
            "MinStockThreshold": 1,
            "QuantityPercent": -1,
            "SpawnAttachments": [],
            "Variants": []
        },
        {
            "ClassName": "My_DF_Weapons_SMG_Vector_20RndMag",
            "MaxPriceThreshold": 1000,
            "MinPriceThreshold": 1000,
            "SellPricePercent": -1,
            "MaxStockThreshold": 1,
            "MinStockThreshold": 1,
            "QuantityPercent": -1,
            "SpawnAttachments": [],
            "Variants": []
        },
        {
            "ClassName": "My_DF_Weapons_SMG_Vector_30RndMag",
            "MaxPriceThreshold": 1000,
            "MinPriceThreshold": 1000,
            "SellPricePercent": -1,
            "MaxStockThreshold": 1,
            "MinStockThreshold": 1,
            "QuantityPercent": -1,
            "SpawnAttachments": [],
            "Variants": []
        },
        {
            "ClassName": "My_DF_Weapons_SMG_Vector_40RndMag",
            "MaxPriceThreshold": 1000,
            "MinPriceThreshold": 1000,
            "SellPricePercent": -1,
            "MaxStockThreshold": 1,
            "MinStockThreshold": 1,
            "QuantityPercent": -1,
            "SpawnAttachments": [],
            "Variants": []
        },
        {
            "ClassName": "My_DF_Weapons_SMG_Vector_70RndMag",
            "MaxPriceThreshold": 1000,
            "MinPriceThreshold": 1000,
            "SellPricePercent": -1,
            "MaxStockThreshold": 1,
            "MinStockThreshold": 1,
            "QuantityPercent": -1,
            "SpawnAttachments": [],
            "Variants": []
        },
        {
            "ClassName": "My_DF_Weapons_Snipers_AWM_5RndMag",
            "MaxPriceThreshold": 1000,
            "MinPriceThreshold": 1000,
            "SellPricePercent": -1,
            "MaxStockThreshold": 1,
            "MinStockThreshold": 1,
            "QuantityPercent": -1,
            "SpawnAttachments": [],
            "Variants": []
        },
        {
            "ClassName": "My_DF_Weapons_Snipers_M700_10RndMag",
            "MaxPriceThreshold": 1000,
            "MinPriceThreshold": 1000,
            "SellPricePercent": -1,
            "MaxStockThreshold": 1,
            "MinStockThreshold": 1,
            "QuantityPercent": -1,
            "SpawnAttachments": [],
            "Variants": []
        },
        {
            "ClassName": "My_DF_Weapons_Snipers_M700_5RndMag",
            "MaxPriceThreshold": 1000,
            "MinPriceThreshold": 1000,
            "SellPricePercent": -1,
            "MaxStockThreshold": 1,
            "MinStockThreshold": 1,
            "QuantityPercent": -1,
            "SpawnAttachments": [],
            "Variants": []
        },
        {
            "ClassName": "My_DF_Weapons_Snipers_R93_10RndMag",
            "MaxPriceThreshold": 1000,
            "MinPriceThreshold": 1000,
            "SellPricePercent": -1,
            "MaxStockThreshold": 1,
            "MinStockThreshold": 1,
            "QuantityPercent": -1,
            "SpawnAttachments": [],
            "Variants": []
        },
        {
            "ClassName": "My_DF_Weapons_Snipers_R93_15RndExtMag",
            "MaxPriceThreshold": 1000,
            "MinPriceThreshold": 1000,
            "SellPricePercent": -1,
            "MaxStockThreshold": 1,
            "MinStockThreshold": 1,
            "QuantityPercent": -1,
            "SpawnAttachments": [],
            "Variants": []
        },
        {
            "ClassName": "My_DF_Weapons_Snipers_SV98_7RndMag",
            "MaxPriceThreshold": 1000,
            "MinPriceThreshold": 1000,
            "SellPricePercent": -1,
            "MaxStockThreshold": 1,
            "MinStockThreshold": 1,
            "QuantityPercent": -1,
            "SpawnAttachments": [],
            "Variants": []
        },
        {
            "ClassName": "My_DF_Weapons_SMG_MK4_24RndMag",
            "MaxPriceThreshold": 1000,
            "MinPriceThreshold": 1000,
            "SellPricePercent": -1,
            "MaxStockThreshold": 1,
            "MinStockThreshold": 1,
            "QuantityPercent": -1,
            "SpawnAttachments": [],
            "Variants": []
        },
        {
            "ClassName": "My_DF_Weapons_SMG_MK4_48RndMag",
            "MaxPriceThreshold": 1000,
            "MinPriceThreshold": 1000,
            "SellPricePercent": -1,
            "MaxStockThreshold": 1,
            "MinStockThreshold": 1,
            "QuantityPercent": -1,
            "SpawnAttachments": [],
            "Variants": []
        }
    ]
}